{
  "kind": "Table",
  "apiVersion": "meta.k8s.io/v1",
  "metadata": {"resourceVersion": "600"},
  "columnDefinitions": [
    {"name": "Name", "type": "string", "format": "name", "priority": 0},
    {"name": "Status", "type": "string", "format": "", "priority": 0},
    {"name": "Roles", "type": "string", "format": "", "priority": 0},
    {"name": "Age", "type": "string", "format": "", "priority": 0},
    {"name": "Version", "type": "string", "format": "", "priority": 0},
    {"name": "Internal-IP", "type": "string", "format": "", "priority": 1},
    {"name": "External-IP", "type": "string", "format": "", "priority": 1},
    {"name": "OS-Image", "type": "string", "format": "", "priority": 1},
    {"name": "Kernel-Version", "type": "string", "format": "", "priority": 1},
    {"name": "Container-Runtime", "type": "string", "format": "", "priority": 1}
  ],
  "rows": [
    {
      "cells": ["worker-1", "Ready", "<none>", "120d", "v1.29.2", "127.0.0.1", "203.0.113.7", "Linux", "6.1.0-18-generic", "containerd://1.7.11"],
      "object": {
        "kind": "Node",
        "apiVersion": "v1",
        "metadata": {
          "name": "worker-1",
          "uid": "00000000-0000-0000-0000-0000000000n9",
          "resourceVersion": "900",
          "creationTimestamp": "2024-02-01T08:00:00Z",
          "labels": {
            "kubernetes.io/hostname": "worker-1",
            "kubernetes.io/os": "linux",
            "kubernetes.io/arch": "amd64"
          }
        },
        "status": {
          "conditions": [
            {"type": "MemoryPressure", "status": "False", "reason": "HasMemory"},
            {"type": "DiskPressure", "status": "False", "reason": "HasDisk"},
            {"type": "PIDPressure", "status": "False", "reason": "HasPID"},
            {"type": "Ready", "status": "True", "reason": "Ready"}
          ],
          "capacity": {
            "cpu": "2",
            "memory": "8047476Ki",
            "pods": "110"
          },
          "allocatable": {
            "cpu": "1930m",
            "memory": "7393076Ki",
            "pods": "110"
          },
          "nodeInfo": {
            "architecture": "amd64",
            "containerRuntimeVersion": "containerd://1.7.11",
            "kernelVersion": "6.1.0-18-generic",
            "kubeletVersion": "v1.29.2",
            "operatingSystem": "linux",
            "osImage": "Linux"
          },
          "addresses": [
            {"type": "InternalIP", "address": "127.0.0.1"},
            {"type": "Hostname", "address": "worker-1"}
          ]
        }
      }
    }
  ]
}
